winnower/__init__.py
winnower/cli.py
winnower/config.py
winnower/core.py
winnower/extractors.py
winnower/formatters.py
winnower/parsers.py
winnower-0.2.2.dist-info/METADATA
winnower-0.2.2.dist-info/WHEEL
winnower-0.2.2.dist-info/entry_points.txt
winnower-0.2.2.dist-info/top_level.txt
winnower-0.2.2.dist-info/RECORD
